kaggle_cli_wrapper/__init__.py
kaggle_cli_wrapper/enums.py
kaggle_cli_wrapper/utils.py
kaggle_cli_wrapper-1.1.dist-info/LICENSE
kaggle_cli_wrapper-1.1.dist-info/METADATA
kaggle_cli_wrapper-1.1.dist-info/WHEEL
kaggle_cli_wrapper-1.1.dist-info/top_level.txt
kaggle_cli_wrapper-1.1.dist-info/RECORD
