Metadata-Version: 2.1
Name: kaggle-cli-wrapper
Version: 1.1
Summary: Kaggle CLI based python wrapper
Home-page: https://github.com/sunny1401/kaggle_utils
Author: Sunny Joshi
Author-email: Sunny Joshi <sunnyjoshi1401@gmail.com>
Project-URL: Homepage, https://github.com/sunny1401/kaggle_utils
Project-URL: Bug Tracker, https://github.com/sunny1401/kaggle_utils/issues
Keywords: Kaggle,API,Wrapper,Python
Classifier: Programming Language :: Python :: 3
Classifier: License :: OSI Approved :: MIT License
Classifier: Operating System :: OS Independent
Classifier: Environment :: No Input/Output (Daemon)
Requires-Python: >=3.7
License-File: LICENSE
